komle/WMLS.WSDL
komle/__init__.py
komle/soap_client.py
komle/uom_converter.py
komle/utils.py
komle/witsmlUnitDict.xml
komle/bindings/__init__.py
komle/bindings/uom.py
komle/bindings/v1411/__init__.py
komle/bindings/v1411/api/__init__.py
komle/bindings/v1411/api/cap_client.py
komle/bindings/v1411/api/cap_server.py
komle/bindings/v1411/read/__init__.py
komle/bindings/v1411/read/_abs.py
komle/bindings/v1411/read/_gco.py
komle/bindings/v1411/read/_gmd.py
komle/bindings/v1411/read/_gml.py
komle/bindings/v1411/read/_gsr.py
komle/bindings/v1411/read/_gss.py
komle/bindings/v1411/read/_gts.py
komle/bindings/v1411/read/_nsgroup.py
komle/bindings/v1411/read/_xlink.py
komle/bindings/v1411/read/witsml.py
komle/bindings/v1411/write/__init__.py
komle/bindings/v1411/write/_abs.py
komle/bindings/v1411/write/_gco.py
komle/bindings/v1411/write/_gmd.py
komle/bindings/v1411/write/_gml.py
komle/bindings/v1411/write/_gsr.py
komle/bindings/v1411/write/_gss.py
komle/bindings/v1411/write/_gts.py
komle/bindings/v1411/write/_nsgroup.py
komle/bindings/v1411/write/_xlink.py
komle/bindings/v1411/write/witsml.py
komle/bindings/v20/__init__.py
komle/bindings/v20/_eml.py
komle/bindings/v20/_gco.py
komle/bindings/v20/_gmd.py
komle/bindings/v20/_gml.py
komle/bindings/v20/_gsr.py
komle/bindings/v20/_gts.py
komle/bindings/v20/_nsgroup.py
komle/bindings/v20/_xlink.py
komle/bindings/v20/witsml.py
komle_plus-0.3.2.3.dist-info/LICENSE
komle_plus-0.3.2.3.dist-info/METADATA
komle_plus-0.3.2.3.dist-info/WHEEL
komle_plus-0.3.2.3.dist-info/top_level.txt
komle_plus-0.3.2.3.dist-info/RECORD
