Metadata-Version: 2.1
Name: komle-plus
Version: 0.3.2.3
Summary: A python library to help with WITSML v1.4.1.1 and v2.0
Home-page: https://github.com/HemersonRafael/komle-plus
Author: HemersonRafael
Author-email: rafaelpontes1995@gmail.com
License: Apache-2.0 License
Keywords: pytohn,soap-client,witsml
Requires-Python: >=3.9
License-File: LICENSE
Requires-Dist: suds-py3 >=1.4.5.0
Requires-Dist: PyXB-X >=1.2.6
Requires-Dist: requests >=2.31.0
Requires-Dist: xmltodict >=0.12.0
